rugo/csv.cpython-310-x86_64-linux-gnu.so
rugo/jsonl.cpython-310-x86_64-linux-gnu.so
rugo/parquet.cpython-310-x86_64-linux-gnu.so
rugo/__init__.py
rugo/csv/csv_reader.pyx
rugo/converters/orso.py
rugo/converters/__init__.py
rugo/jsonl/jsonl_reader.pyx
rugo/parquet/parquet_reader.pyx
rugo/parquet/parquet_reader.pxd
rugo-0.1.19.dist-info/WHEEL
rugo-0.1.19.dist-info/top_level.txt
rugo-0.1.19.dist-info/METADATA
rugo-0.1.19.dist-info/RECORD
rugo-0.1.19.dist-info/licenses/LICENSE
