Metadata-Version: 2.4
Name: rugo
Version: 0.1.19
Summary: Parquet Metadata Reader
Author-email: Justin Joyce <justin.joyce@joocer.com>
License:                                  Apache License
Project-URL: Homepage, https://github.com/mabel-dev/rugo
Project-URL: Repository, https://github.com/mabel-dev/rugo
Project-URL: Issues, https://github.com/mabel-dev/rugo/issues
Keywords: data,decoder,parquet,cython,python
Classifier: Development Status :: 3 - Alpha
Classifier: Intended Audience :: Developers
Classifier: Programming Language :: Python :: 3
Classifier: Programming Language :: Python :: 3.9
Classifier: Programming Language :: Python :: 3.10
Classifier: Programming Language :: Python :: 3.11
Classifier: Programming Language :: Python :: 3.12
Classifier: Programming Language :: Python :: 3.13
Classifier: Programming Language :: Cython
Classifier: Topic :: Software Development :: Libraries
Classifier: Topic :: System :: Archiving
Requires-Python: >=3.9
License-File: LICENSE
Provides-Extra: dev
Requires-Dist: pytest>=6.0.0; extra == "dev"
Requires-Dist: pytest-cov; extra == "dev"
Requires-Dist: build; extra == "dev"
Requires-Dist: twine; extra == "dev"
Provides-Extra: test
Requires-Dist: orso; extra == "test"
Requires-Dist: pyarrow; extra == "test"
Requires-Dist: pytest>=6.0.0; extra == "test"
Requires-Dist: pytest-cov; extra == "test"
Provides-Extra: orso
Requires-Dist: orso>=0.0.200; extra == "orso"
Dynamic: license-file
